{
    "ignorePatterns": [
        {
            "pattern": "^https://support.discord.com/hc/en-us/articles/216273938-How-do-I-transfer-server-ownership"
        },
        {
            "pattern": "^https://www.dcode.fr/en"
        },
        {
            "pattern": "^https://developer.android.com/studio/build/configure-app-module"
        }
    ],
    "timeout": "20s",
    "retryOn429": true,
    "retryCount": 5,
    "fallbackRetryDelay": "30s",
    "aliveStatusCodes": [
        200,
        403,
        429
    ]
}